Workbook

Sheet PENDIENTES EXTRACTO
A1: INFORMACION INICIAL CARGUE BANCOS
A2: CODIGO BANCO | B2: TIPO DE CUENTA | C2: NUMERO DE CUENTA | D2: FECHA DE MOVIMIENTO | E2: REFERENCIA 1 | F2: REFERENCIA 2 | G2: REFERENCIA 3 | H2: DESCRIPCION | I2: VALOR CREDITO | J2: VALOR DEBITO
A3: 7 | B3: cta cte | C3: 039-137051-24 | D3: 44043 | H3: IVA COMISION RECAUDOS CAJEROS | I3: 0 | J3: 217.53
A4: 7 | B4: cta cte | C4: 039-137051-24 | D4: 44043 | H4: 4XMIL GRAVAMEN MVTO FINANCIERO | I4: 0 | J4: 1057.8
A5: 7 | B5: cta cte | C5: 039-137051-24 | D5: 44043 | H5: IVA POR SERVICIO DE RECAUDO | I5: 0 | J5: 1339.5
A6: 7 | B6: cta cte | C6: 039-137051-24 | D6: 44043 | H6: IVA COMISION RECAUDOS CAJA | I6: 0 | J6: 6764
A7: 7 | B7: cta cte | C7: 039-137051-24 | D7: 44043 | H7: IVA COMISION RECAUDOS CAJA | I7: 0 | J7: 8455
A8: 7 | B8: cta cte | C8: 039-137051-24 | D8: 44043 | H8: IVA POR SERVICIO DE RECAUDO | I8: 0 | J8: 10716
A9: 7 | B9: cta cte | C9: 039-137051-24 | D9: 44043 | H9: IVA COMISION RECAUDOS CB | I9: 0 | J9: 14730.43
A10: 7 | B10: cta cte | C10: 039-137051-24 | D10: 44032 | E10: 9175015594901827 | H10: PAGO PROGRAMADO MOVISTAR FIJO | I10: 0 | J10: 147408
A11: 7 | B11: cta cte | C11: 039-356629-46 | D11: 44043 | E11: 3201344815 | H11: TRANSFERENCIA CTA SUC VIRTUAL | I11: 280000 | J11: 0
A12: 7 | B12: cta cte | C12: 039-356629-46 | D12: 44043 | E12: TESSI GESTIONA S | F12: TESSI GESTIONA S | H12: PAGO DE PROV TESSI GESTIONA S | I12: 640056 | J12: 0
A13: 7 | B13: cta cte | C13: 039-356629-46 | D13: 44043 | E13: 79367842 | H13: CONSIG LOCAL REFEREN EFECTIVO | I13: 1500000 | J13: 0
A14: 7 | B14: cta cte | C14: 039-356629-46 | D14: 44043 | E14: 8300531806 | H14: CONSIG LOCAL REFEREN EFECTIVO | I14: 2623865 | J14: 0
A15: 7 | B15: cta cte | C15: 039-356629-46 | D15: 44043 | E15: 36169786 | H15: CONSIG NAL REFERENCIA EFECTIVO | I15: 2785000 | J15: 0
A16: 7 | B16: cta cte | C16: 039-356629-46 | D16: 44042 | E16: 20795788170 | H16: TRANSFERENCIA CTA SUC VIRTUAL | I16: 5500000 | J16: 0
A17: 7 | B17: cta cte | C17: 039-356629-46 | D17: 44043 | E17: 3065621621 | H17: TRANSFERENCIA CTA SUC VIRTUAL | I17: 5600000 | J17: 0
A18: 7 | B18: cta cte | C18: 039-356629-46 | D18: 44043 | E18: 51586102 | H18: PAGO INTERBANC SANCHEZ MORENO | I18: 9000000 | J18: 0
A19: 7 | B19: cta cte | C19: 039-356629-46 | D19: 44043 | E19: ALFONSO URIBE S | F19: ALFONSO URIBE S | H19: PAGO DE PROV ALFONSO URIBE S | I19: 13820806 | J19: 0
A20: 7 | B20: cta cte | C20: 039-356629-46 | D20: 44043 | E20: 41557894 | H20: CONSIG LOCAL REFEREN EFECTIVO | I20: 20000000 | J20: 0
A21: 7 | B21: cta cte | C21: 039-356629-46 | D21: 44043 | E21: 860007327105 | H21: CONSIG LOCAL REFERENCIA CANJE | I21: 22177133 | J21: 0
A22: 7 | B22: cta cte | C22: 039-356629-46 | D22: 44042 | H22: TRASL ENTRE FONDOS DE VALORES | I22: 260000000 | J22: 0
A23: 7 | B23: cta cte | C23: 039-356629-46 | D23: 44042 | H23: 4XMIL GRAVAMEN MVTO FINANCIERO | I23: 0 | J23: 50.93
A24: 7 | B24: cta cte | C24: 039-356629-46 | D24: 44043 | H24: 4XMIL GRAVAMEN MVTO FINANCIERO | I24: 0 | J24: 118.76
A25: 7 | B25: cta cte | C25: 039-356629-46 | D25: 44043 | H25: IVA COMISION RECAUDOS CAJA | I25: 0 | J25: 845.5
A26: 7 | B26: cta cte | C26: 039-356629-46 | D26: 44043 | H26: IVA COMISION RECAUDOS CAJA | I26: 0 | J26: 845.5
A27: 7 | B27: cta cte | C27: 039-356629-46 | D27: 44042 | H27: IVA COMISION RECAUDOS CAJA | I27: 0 | J27: 2033
A28: 7 | B28: cta cte | C28: 039-356629-46 | D28: 44043 | H28: IVA COMISION RECAUDOS CAJA | I28: 0 | J28: 3049.5
A29: 7 | B29: cta cte | C29: 039-356629-46 | D29: 44043 | H29: COMISION CAJA CODIGO DE BARRAS | I29: 0 | J29: 4450
A30: 7 | B30: cta cte | C30: 039-356629-46 | D30: 44043 | H30: COMISION CAJA CODIGO DE BARRAS | I30: 0 | J30: 4450
A31: 7 | B31: cta cte | C31: 039-356629-46 | D31: 44042 | H31: COMISION RECAUDOS CAJA LOCAL | I31: 0 | J31: 10700
A32: 7 | B32: cta cte | C32: 039-356629-46 | D32: 44043 | H32: COMISION RECAUDOS CAJA LOCAL | I32: 0 | J32: 16050
A33: 7 | B33: cta cte | C33: 039-356629-46 | D33: 44026 | H33: DEV CONSIGN NAL CAUSAL 18 | I33: 0 | J33: 79605033
A34: 23 | B34: cta cte | C34: 242057271 | D34: 44034 | H34: CARGO POR OTROS CONCEPTOS SIN GMF | I34: 0 | J34: 180000
A35: 23 | B35: cta cte | C35: 242057271 | D35: 43977 | H35: CARGO POR OTROS CONCEPTOS SIN GMF | I35: 0 | J35: 289000
A36: 23 | B36: cta cte | C36: 265056630 | D36: 44043 | H36: SIN MOVIMIENTO | I36: 0 | J36: 0
I37: =SUM(I3:I36) -> 343926860
A39: TOTALES | I39: =SUM(I3:I38) -> 687853720 | J39: =SUM(J3:J38) -> 80307314
A41: Fecha Movimiento | B41: Código Transacción | C41: Descripccion | D41: Documento | E41: Débitos | F41: Créditos | G41: Referencia1 | H41: Referencia2 | I41: Valor Efectivo | J41: Valor Cheque
A42: 44047 | B42: 5503 | C42: IVA | D42: 0 | E42: 2679 | F42: 0 | G42: - | H42: - | I42: $0,00 | J42: $0,00
A43: 44047 | B43: 805 | C43: CODIGO DE BARRAS | D43: A738471 | E43: 0 | F43: 529718 | G43: - | H43: - | I43: $0,00 | J43: $0,00
A44: 44047 | B44: 1103 | C44: COMISION CODIGO DE BARRAS | D44: 0 | E44: 14100 | F44: 0 | G44: - | H44: - | I44: $0,00 | J44: $0,00
A45: occidente 6630 | E45: =SUM(E42:E44) -> 16779 | F45: =SUM(F42:F44) -> 529718
A47: Fecha Movimiento | B47: Código Transacción | C47: Nombre Transacción | D47: Documento | E47: Débitos | F47: Créditos | G47: Referencia1 | H47: Referencia2 | I47: Valor Efectivo | J47: Valor Cheque
A48: 2020/08/03 | B48: 2903 | C48: GMF | D48: 0000000 | E48: 256.56 | F48: 0 | G48: - | H48: - | I48: $0,00 | J48: $0,00
A49: 2020/08/03 | B49: 6503 | C49: CUOTA DE MANEJO RED PUBLICA INTERNET | D49: A219729 | E49: 56000 | F49: 0 | G49: - | H49: - | I49: $0,00 | J49: $0,00
A50: 2020/08/03 | B50: 5503 | C50: IVA COBRADO | D50: A219760 | E50: 10640 | F50: 0 | G50: - | H50: - | I50: $0,00 | J50: $0,00
A51: 2020/08/03 | B51: 1105 | C51: RECAUDO/PAGO SERVICIOS ELECT | D51: A643388 | E51: 0 | F51: 12374121 | G51: - | H51: - | I51: $0,00 | J51: $0,00
A52: 2020/08/04 | B52: 1105 | C52: RECAUDO/PAGO SERVICIOS ELECT | D52: A878193 | E52: 0 | F52: 7468660 | G52: - | H52: - | I52: $0,00 | J52: $0,00
A53: 2020/08/04 | B53: 9205 | C53: PAGO TERCERO RECIBIDO DESDE ACH | D53: A875192 | E53: 0 | F53: 15000 | G53: - | H53: - | I53: $0,00 | J53: $0,00
E54: =SUM(E48:E53) -> 66896.56 | F54: =SUM(F48:F53) -> 19857781
A55: occidente 7271
A57: 0 | B57: BOGOTA | C57: 039-356629-46 | D57: 7081 | E57: DEV CHEQUE CONSIG CAUSAL 14 | F57: 768539 | G57: 20200804 | H57: CARRERA OCTAVA | I57: 30 | J57: 9001469504 | K57: 1 | L57: -5473473
A58: 0 | B58: BOGOTA | C58: 039-356629-46 | D58: 5537 | E58: COMISION RECAUDOS CAJA LOCAL | F58: 0 | G58: 20200803 | H58: ECOPETROL | I58: 39 | K58: 1 | L58: -21400
A59: 0 | B59: BOGOTA | C59: 039-356629-46 | D59: 5537 | E59: COMISION RECAUDOS CAJA LOCAL | F59: 0 | G59: 20200804 | H59: ECOPETROL | I59: 39 | K59: 1 | L59: -5350
A60: 0 | B60: BOGOTA | C60: 039-356629-46 | D60: 5539 | E60: COMIS RECAUDOS CAJA NACIONAL | F60: 0 | G60: 20200804 | H60: ECOPETROL | I60: 39 | K60: 1 | L60: -5350
A61: 0 | B61: BOGOTA | C61: 039-356629-46 | D61: 7525 | E61: IVA COMISION RECAUDOS CAJA | F61: 0 | G61: 20200803 | H61: ECOPETROL | I61: 39 | K61: 1 | L61: -4066
A62: 0 | B62: BOGOTA | C62: 039-356629-46 | D62: 7525 | E62: IVA COMISION RECAUDOS CAJA | F62: 0 | G62: 20200804 | H62: ECOPETROL | I62: 39 | K62: 1 | L62: -1016.5
A63: 0 | B63: BOGOTA | C63: 039-356629-46 | D63: 7525 | E63: IVA COMISION RECAUDOS CAJA | F63: 0 | G63: 20200804 | H63: ECOPETROL | I63: 39 | K63: 1 | L63: -1016.5
A64: 0 | B64: BOGOTA | C64: 039-356629-46 | D64: 3339 | E64: 4XMIL GRAVAMEN MVTO FINANCIERO | F64: 0 | G64: 20200803 | H64: ECOPETROL | I64: 39 | K64: 1 | L64: -101.86
A65: 0 | B65: BOGOTA | C65: 039-356629-46 | D65: 3339 | E65: 4XMIL GRAVAMEN MVTO FINANCIERO | F65: 0 | G65: 20200804 | H65: ECOPETROL | I65: 39 | K65: 1 | L65: -50.93
L66: -5511824.8
A67: 0 | B67: BOGOTA | C67: 039-356629-46 | D67: 7891 | E67: TRANSFERENCIA DESDE NEQUI | F67: 0 | G67: 20200804 | H67: ECOPETROL | I67: 39 | J67: JORGE ROJAS 3035 | K67: 1 | L67: 70000
A68: 0 | B68: PALMIRA | C68: 039-356629-46 | D68: 4018 | E68: CONSIG NAL REFERENCIA CHEQUE | F68: 0 | G68: 20200804 | H68: PALMIRA | I68: 66 | J68: 900392806 | K68: 1 | L68: 322805
A69: 0 | B69: BOGOTA | C69: 039-356629-46 | D69: 4014 | E69: CONSIG LOCAL REFERENCIA CANJE | F69: 0 | G69: 20200803 | H69: WORLD TRADE CENTER | I69: 304 | J69: 8001496951 | K69: 1 | L69: 418683
A70: 0 | B70: BOGOTA | C70: 039-356629-46 | D70: 4013 | E70: CONSIG LOCAL REFEREN EFECTIVO | F70: 0 | G70: 20200803 | H70: NORTH POINT | I70: 743 | J70: 79367842 | K70: 1 | L70: 550000
A71: 0 | B71: BOGOTA | C71: 039-356629-46 | D71: 8161 | E71: PAGO DE PROV AMERICAS BUSINES | F71: 0 | G71: 20200803 | H71: ECOPETROL | I71: 39 | J71: AMERICAS BUSINES | K71: 1 | L71: 698990
A72: 0 | B72: BOGOTA | C72: 039-356629-46 | D72: 4160 | E72: TRANSFERENCIA CTA SUC VIRTUAL | F72: 0 | G72: 20200804 | H72: ECOPETROL | I72: 39 | J72: 3065621621 | K72: 1 | L72: 1000000
A73: 0 | B73: BOGOTA | C73: 039-356629-46 | D73: 8142 | E73: PAGO INTERBANC Laboratorios Ry | F73: 0 | G73: 20200804 | H73: ECOPETROL | I73: 39 | J73: 8600292375 | K73: 1 | L73: 1898248
A74: 0 | B74: BOGOTA | C74: 039-356629-46 | D74: 4160 | E74: TRANSFERENCIA CTA SUC VIRTUAL | F74: 0 | G74: 20200801 | H74: ECOPETROL | I74: 39 | J74: 17488876287 | K74: 1 | L74: 2000000
A75: 0 | B75: BOGOTA | C75: 039-356629-46 | D75: 4160 | E75: TRANSFERENCIA CTA SUC VIRTUAL | F75: 0 | G75: 20200801 | H75: ECOPETROL | I75: 39 | J75: 3065621621 | K75: 1 | L75: 2400000
A76: 0 | B76: BOGOTA | C76: 039-356629-46 | D76: 4160 | E76: TRANSFERENCIA CTA SUC VIRTUAL | F76: 0 | G76: 20200804 | H76: ECOPETROL | I76: 39 | J76: 22930538829 | K76: 1 | L76: 3000000
A77: 0 | B77: BOGOTA | C77: 039-356629-46 | D77: 4014 | E77: CONSIG LOCAL REFERENCIA CANJE | F77: 0 | G77: 20200804 | H77: LA GRAN ESTACION | I77: 299 | J77: 9001469504 | K77: 1 | L77: 5473473
A78: 0 | B78: BOGOTA | C78: 039-356629-46 | D78: 4014 | E78: CONSIG LOCAL REFERENCIA CANJE | F78: 0 | G78: 20200803 | H78: EXITO NORTE | I78: 932 | J78: 8.6E+11 | K78: 1 | L78: 59883292
A79: 0 | B79: BOGOTA | C79: 039-356629-46 | D79: 4014 | E79: CONSIG LOCAL REFERENCIA CANJE | F79: 0 | G79: 20200803 | H79: CENTRO COMERCIAL FON | I79: 682 | J79: 1113308095 | K79: 1 | L79: 600000000
B80: CIUDAD | C80: NUMERO DE CUENTA | D80: CODIGO DE TRANSACCION | E80: DESCRIPCCION | G80: FECHA MOVIMIENTO | H80: NOMBRE OFICINA | I80: CODIGO OFICINA | J80: REF 1 | L80: 677715491
A82: colombia 2946
A84: 0 | B84: BOGOTA | C84: 039-137051-24 | D84: 7552 | E84: PAGO DEBITO AUTO. BANCOLOMBI | F84: 0 | G84: 20200803 | H84: ECOPETROL | I84: 39 | J84: DEBITO AUTO.BANCOLOMBIA LRYU | K84: 1 | L84: -4166857
A85: 0 | B85: BOGOTA | C85: 039-137051-24 | D85: 815 | E85: COMISION CB CODIGO DE BARRAS | F85: 0 | G85: 20200804 | H85: ECOPETROL | I85: 39 | K85: 1 | L85: -89461.35
A86: 0 | B86: BOGOTA | C86: 039-137051-24 | D86: 1340 | E86: COMISION CAJA CODIGO DE BARRAS | F86: 0 | G86: 20200804 | H86: ECOPETROL | I86: 39 | K86: 1 | L86: -84550
A87: 0 | B87: BOGOTA | C87: 039-137051-24 | D87: 815 | E87: COMISION CB CODIGO DE BARRAS | F87: 0 | G87: 20200803 | H87: ECOPETROL | I87: 39 | K87: 1 | L87: -72653.46
A88: 0 | B88: BOGOTA | C88: 039-137051-24 | D88: 1340 | E88: COMISION CAJA CODIGO DE BARRAS | F88: 0 | G88: 20200804 | H88: ECOPETROL | I88: 39 | K88: 1 | L88: -66750
A89: 0 | B89: BOGOTA | C89: 039-137051-24 | D89: 1340 | E89: COMISION CAJA CODIGO DE BARRAS | F89: 0 | G89: 20200803 | H89: ECOPETROL | I89: 39 | K89: 1 | L89: -40050
A90: 0 | B90: BOGOTA | C90: 039-137051-24 | D90: 7181 | E90: COMIS SERVICIOS DE RECAUDO | F90: 0 | G90: 20200801 | H90: ECOPETROL | I90: 39 | K90: 1 | L90: -37600
A91: 0 | B91: BOGOTA | C91: 039-137051-24 | D91: 7181 | E91: COMIS SERVICIOS DE RECAUDO | F91: 0 | G91: 20200803 | H91: ECOPETROL | I91: 39 | K91: 1 | L91: -37600
A92: 0 | B92: BOGOTA | C92: 039-137051-24 | D92: 7181 | E92: COMIS SERVICIOS DE RECAUDO | F92: 0 | G92: 20200802 | H92: ECOPETROL | I92: 39 | K92: 1 | L92: -32900
A93: 0 | B93: BOGOTA | C93: 039-137051-24 | D93: 7181 | E93: COMIS SERVICIOS DE RECAUDO | F93: 0 | G93: 20200804 | H93: ECOPETROL | I93: 39 | K93: 1 | L93: -32900
A94: 0 | B94: BOGOTA | C94: 039-137051-24 | D94: 815 | E94: COMISION CB CODIGO DE BARRAS | F94: 0 | G94: 20200801 | H94: ECOPETROL | I94: 39 | K94: 1 | L94: -28193.88
A95: 0 | B95: BOGOTA | C95: 039-137051-24 | D95: 1340 | E95: COMISION CAJA CODIGO DE BARRAS | F95: 0 | G95: 20200803 | H95: ECOPETROL | I95: 39 | K95: 1 | L95: -26700
A96: 0 | B96: BOGOTA | C96: 039-137051-24 | D96: 3339 | E96: 4XMIL GRAVAMEN MVTO FINANCIERO | F96: 0 | G96: 20200803 | H96: ECOPETROL | I96: 39 | K96: 1 | L96: -17571.34
... A124: 0 | B124: BOGOTA | C124: 039-137051-24 | D124: 3339 | E124: 4XMIL GRAVAMEN MVTO FINANCIERO | F124: 0 | G124: 20200802 | H124: ECOPETROL | I124: 39 | K124: 1 | L124: -185.85
L125: -4878028.9
A126: 0 | B126: BOGOTA | C126: 039-137051-24 | D126: 6842 | E126: CONSIG REFER BCA ELECTRONICA | F126: 0 | G126: 20200801 | H126: ECOPETROL | I126: 39 | J126: 45467217 | K126: 1 | L126: 55
A127: 0 | B127: MEDELLIN | C127: 039-137051-24 | D127: 4017 | E127: CONSIG NAL REFERENCIA EFECTIVO | F127: 0 | G127: 20200804 | H127: BARRIO TRISTE | I127: 625 | J127: 163201000000000000 | K127: 1 | L127: 2269
A128: 0 | B128: MEDELLIN | C128: 039-137051-24 | D128: 4013 | E128: CONSIG LOCAL REFEREN EFECTIVO | F128: 0 | G128: 20200804 | H128: CNB REDES | I128: 917 | J128: 432704000000000000 | K128: 1 | L128: 6500
A129: 0 | B129: MEDELLIN | C129: 039-137051-24 | D129: 4013 | E129: CONSIG LOCAL REFEREN EFECTIVO | F129: 0 | G129: 20200801 | H129: CNB REDES | I129: 917 | J129: 202301000000000000 | K129: 1 | L129: 8000
A130: 0 | B130: MEDELLIN | C130: 039-137051-24 | D130: 4013 | E130: CONSIG LOCAL REFEREN EFECTIVO | F130: 0 | G130: 20200804 | H130: CNB REDES | I130: 917 | J130: 180101000000000000 | K130: 1 | L130: 8000
A131: 0 | B131: MEDELLIN | C131: 039-137051-24 | D131: 4013 | E131: CONSIG LOCAL REFEREN EFECTIVO | F131: 0 | G131: 20200803 | H131: CNB REDES | I131: 917 | J131: 433201000000000000 | K131: 1 | L131: 9000
A132: 0 | B132: MEDELLIN | C132: 039-137051-24 | D132: 4013 | E132: CONSIG LOCAL REFEREN EFECTIVO | F132: 0 | G132: 20200804 | H132: CNB REDES | I132: 917 | J132: 982980000000000000 | K132: 1 | L132: 9100
A133: 0 | B133: BOGOTA | C133: 039-137051-24 | D133: 6842 | E133: CONSIG REFER BCA ELECTRONICA | F133: 0 | G133: 20200804 | H133: ECOPETROL | I133: 39 | J133: 1052416384 | K133: 1 | L133: 9528
...

Sheet PENDIENTES LIBROS
A1: INFORMACION INICIAL CARGUE AUXILIAR CONTABLE
A2: NUMERO DE CUENTA CONTABLE | B2: CODIGO BANCO | C2: TIPO DE CUENTA | D2: NUMERO DE CUENTA BANCARIA | E2: FECHA DE MOVIMIENTO | F2: COMPROBANTE CONTABLE | G2: REFERENCIA 1 | H2: TERCERO | I2: DESCRIPCION | J2: VALOR DEBITO | K2: VALOR CREDITO
A3: 111005100012 | B3: 7 | C3: cta cte | D3: 039-137051-24 | E3: 44043 | G3: 890903938 | I3: "FNCLUZMAT"-IVA COMISION RECAUDOS CAJEROS-BANCOLOMBIA | J3: 0 | K3: 217.53
A4: 111005100012 | B4: 7 | C4: cta cte | D4: 039-137051-24 | E4: 44043 | G4: 890903938 | I4: "FNCLUZMAT"-4XMIL GRAVAMEN MVTO FINANCIERO-BANCOLOMBIA | J4: 0 | K4: 1057.8
A5: 111005100012 | B5: 7 | C5: cta cte | D5: 039-137051-24 | E5: 44043 | G5: 890903938 | I5: "FNCLUZMAT"-IVA POR SERVICIO DE RECAUDO-BANCOLOMBIA | J5: 0 | K5: 1339.5
A6: 111005100012 | B6: 7 | C6: cta cte | D6: 039-137051-24 | E6: 44043 | G6: 890903938 | I6: "FNCLUZMAT"-IVA COMISION RECAUDOS CAJA-BANCOLOMBIA | J6: 0 | K6: 6764
A7: 111005100012 | B7: 7 | C7: cta cte | D7: 039-137051-24 | E7: 44043 | G7: 890903938 | I7: "FNCLUZMAT"-IVA COMISION RECAUDOS CAJA-BANCOLOMBIA | J7: 0 | K7: 8455
A8: 111005100012 | B8: 7 | C8: cta cte | D8: 039-137051-24 | E8: 44043 | G8: 890903938 | I8: "FNCLUZMAT"-IVA POR SERVICIO DE RECAUDO-BANCOLOMBIA | J8: 0 | K8: 10716
A9: 111005100012 | B9: 7 | C9: cta cte | D9: 039-137051-24 | E9: 44043 | G9: 890903938 | I9: "FNCLUZMAT"-IVA COMISION RECAUDOS CB-BANCOLOMBIA | J9: 0 | K9: 14730.43
A10: 111005100025 | B10: 7 | C10: cta cte | D10: 039-356629-46 | E10: 44043 | G10: 1 | I10: Bancos ASOBANCARIA-Identificacion No Exste | J10: 280000 | K10: 0
A11: 111005100025 | B11: 7 | C11: cta cte | D11: 039-356629-46 | E11: 44043 | G11: 1 | I11: Bancos ASOBANCARIA-Identificacion No Exste | J11: 640056 | K11: 0
A12: 111005100025 | B12: 7 | C12: cta cte | D12: 039-356629-46 | E12: 44043 | G12: 79367842 | I12: Bancos ASOBANCARIA-ROJAS QUIMBAYA JORGE HERNAN | J12: 1500000 | K12: 0
A13: 111005100025 | B13: 7 | C13: cta cte | D13: 039-356629-46 | E13: 44043 | G13: 1 | I13: Bancos ASOBANCARIA-Identificacion No Exste | J13: 2000000 | K13: 0
A14: 111005100025 | B14: 7 | C14: cta cte | D14: 039-356629-46 | E14: 44043 | G14: 830053180 | I14: Bancos ASOBANCARIA-CONSERVAS DELCASINO S.A | J14: 2623865 | K14: 0
... A34: 111005100025 | B34: 7 | C34: cta cte | D34: 039-356629-46 | E34: 44043 | G34: 890903938 | I34: COMISION RECAUDOS CAJA LOCAL-BANCOLOMBIA | J34: 0 | K34: 16050
A35: 111005100003 | B35: 23 | C35: cta cte | D35: 242057271 | E35: 44043 | I35: SIN MOVIMIENTO | J35: 0 | K35: 0
A36: 1110005100024 | B36: 23 | C36: cta cte | D36: 265056630 | E36: 44043 | I36: SIN MOVIMIENTO | J36: 0 | K36: 0
A38: TOTALES | J38: =SUM(J3:J37) -> 427987285 | K38: =SUM(K3:K37) -> 85873.45

Sheet CUADRE INICIAL
C1: COLOMBIA | D1: COLOMBIA | E1: OCCIDENTE | F1: OCCIDENTE | G1: CONCILIACION INICIAL
A2: CUADRE A JULIO 30 DE 2.020 | B2: TIPO DE CARGUE | C2: 039-137051-24 | D2: 039-356629-46 | E2: 242057271 | F2: 265056630
C3: 111005100012 | D3: 111005100025 | E3: 111005100003 | F3: 111005100024
A4: SALDO BANCOS | B4: MANUAL | C4: 5.929464e+08 | D4: 6.9674951e+08 | E4: 2965931.6 | F4: 904945.32
A5: DEBITO LIBROS | B5: PLANTILLA | C5: 0 | D5: =SUM('PENDIENTES LIBROS'!J10:J34) -> 427987285 | E5: =SUM('PENDIENTES LIBROS'!J35) -> 0 | F5: =SUM('PENDIENTES LIBROS'!J36) -> 0
A6: CREDITO BANCOS | B6: PLANTILLA | C6: =SUM('PENDIENTES EXTRACTO'!I3:I10) -> 0 | D6: =SUM('PENDIENTES EXTRACTO'!I11:I33) -> 343926860 | E6: =SUM('PENDIENTES EXTRACTO'!I34:I35) -> 0 | F6: =SUM('PENDIENTES EXTRACTO'!J36) -> 0
A7: DEBITO BANCO | B7: PLANTILLA | C7: =SUM('PENDIENTES EXTRACTO'!J3:J10) -> 190688.26 | D7: =SUM('PENDIENTES EXTRACTO'!J11:J33) -> 79647626 | E7: =SUM('PENDIENTES EXTRACTO'!J34:J35) -> 469000 | F7: =SUM('PENDIENTES EXTRACTO'!I36) -> 0
A8: CREDITO LIBROS | B8: PLANTILLA | C8: =SUM('PENDIENTES LIBROS'!K3:K9) -> 43280.26 | D8: =SUM('PENDIENTES LIBROS'!K10:K34) -> 42593.19 | E8: =SUM('PENDIENTES LIBROS'!K35) -> 0 | F8: ='PENDIENTES LIBROS'!K36 -> 0
A9: TOTAL | B9: FORMULA | C9: =+C4+C5-C6+C7-C8 -> 5.9309381e+08 | D9: =+D4+D5-D6+D7-D8 -> 8.6041497e+08 | E9: =+E4+E5-E6+E7-E8 -> 3434931.6 | F9: =+F4+F5-F6+F7-F8 -> 904945.32
A10: SALDO LIBROS | B10: MANUAL | C10: 5.9309381e+08 | D10: 8.6041497e+08 | E10: 3434931.6 | F10: 904945.32
A11: DIFERENCIA | B11: DEBE SER CERO | C11: =+C9-C10 -> 0 | D11: =+D9-D10 -> 0 | E11: =+E9-E10 -> 0 | F11: =+F9-F10 -> 0
C14: COLOMBIA | D14: COLOMBIA | E14: OCCIDENTE | F14: OCCIDENTE | G14: CUADRE MOVIMIENTO BANCOS 1 A 4 AGOSTO
A15: CUADRE A JULIO 30 DE 2.020 | B15: TIPO DE CARGUE | C15: 039-137051-24 | D15: 039-356629-46 | E15: 242057271 | F15: 265056630
C16: 111005100012 | D16: 111005100025 | E16: 111005100003 | F16: 111005100024
A17: SALDO BANCOS | B17: AUTOMATICO | C17: 5.929464e+08 | D17: 6.9674951e+08 | E17: 2965931.6 | F17: 904945.32
A18: DEBITO BANCOS | B18: EXTRACTO | C18: =SUM(C38) -> 4878028.9 | D18: =SUM(D38) -> 5511824.8 | E18: =SUM(E38) -> 66896.56 | F18: =SUM(F38) -> 16779
A19: CREDITO BANCOS | B19: EXTRACTO | C19: =SUM(C37) -> 1.9688622e+08 | D19: =SUM(D37) -> 6.7771547e+08 | E19: =SUM(E37) -> 19857781 | F19: =SUM(F37) -> 529718
A20: SALDO BANCOAGOSTO 4 | B20: FORMULA | C20: =SUM(C17-C18+C19) -> 7.8495459e+08 | D20: =SUM(D17-D18+D19) -> 1.3689532e+09 | E20: =SUM(E17-E18+E19) -> 22756816 | F20: =SUM(F17-F18+F19) -> 1417884.3
A21: SALDO BANCO MANUAL | B21: MANUAL | C21: 7.8495459e+08 | D21: 1.3689532e+09 | E21: 22756816 | F21: 1417884.3
A22: DIFERENCIA | B22: DEBE SER CERO | C22: =SUM(C20-C21) -> 0 | D22: =SUM(D20-D21) -> -2.3841858e-07 | E22: =SUM(E20-E21) -> 0 | F22: =SUM(F20-F21) -> -2.3283064e-10
A23: SALDO LIBROS | B23: AUTOMATICO | C23: 5.9309381e+08 | D23: 8.6041497e+08 | E23: 3434931.6 | F23: 904945.32 | G23: CUADRE MOVIMIENTO CONTABLE 1 A 4 AGOSTO
A24: DEBITO LIBROS | B24: PLANTILLA | C24: =SUM(C36) -> 1.9531116e+08 | D24: =SUM(D36) -> 771282870 | E24: =SUM(E36) -> 12374121 | F24: =SUM(F36) -> 529718
A25: CREDITO LIBROS | B25: PLANTILLA | C25: =SUM(C39) -> 711171.9 | D25: =SUM(D39) -> 1.6170381e+08 | E25: =SUM(E39) -> 66906.56 | F25: =SUM(F39) -> 16779
A26: SALDO CONTABILIDAD AGOSTO 4 | B26: FORMULA | C26: =SUM(C23+C24-C25) -> 7.876938e+08 | D26: =SUM(D23+D24-D25) -> 1.469994e+09 | E26: =SUM(E23+E24-E25) -> 15742146 | F26: =SUM(F23+F24-F25) -> 1417884.3
A27: SALDO CONTABILIDAD AGOSTO 4 | B27: MANUAL | C27: 7.876938e+08 | D27: 1.469994e+09 | E27: 15742146 | F27: 1417884.3
A28: DIFERENCIA | B28: DEBE SER CERO | C28: =SUM(C26-C27) -> 0 | D28: =SUM(D26-D27) -> 0 | E28: =SUM(E26-E27) -> 0 | F28: =SUM(F26-F27) -> -2.3283064e-10
C32: COLOMBIA | D32: COLOMBIA | E32: OCCIDENTE | F32: OCCIDENTE | J32: =6580+230+210 -> 7020
A33: MOVIMIENTO 1 AL 4 agosto | B33: TIPO DE CARGUE | C33: 039-137051-24 | D33: 039-356629-46 | E33: 242057271 | F33: 265056630
C34: 111005100012 | D34: 111005100025 | E34: 111005100003 | F34: 111005100024
A35: SALDO BANCOS | B35: MANUAL | C35: =SUM(C20) -> 7.8495459e+08 | D35: =SUM(D20) -> 1.3689532e+09 | E35: =SUM(E20) -> 22756816 | F35: =SUM(F20) -> 1417884.3
A36: DEBITO LIBROS | B36: PLANTILLA | C36: 1.9531116e+08 | D36: 771282870 | E36: 12374121 | F36: 529718
A37: CREDITO BANCOS | B37: PLANTILLA | C37: =SUM('PENDIENTES EXTRACTO'!L607) -> 1.9688622e+08 | D37: 6.7771547e+08 | E37: =SUM('PENDIENTES EXTRACTO'!F54) -> 19857781 | F37: =SUM('PENDIENTES EXTRACTO'!F45) -> 529718 | I37: saldos igual mdp
A38: DEBITO BANCO | B38: PLANTILLA | C38: 4878028.9 | D38: 5511824.8 | E38: =SUM('PENDIENTES EXTRACTO'!E54) -> 66896.56 | F38: =SUM('PENDIENTES EXTRACTO'!E45) -> 16779 | I38: Saldos diferentes MDP
A39: CREDITO LIBROS | B39: PLANTILLA | C39: 711171.9 | D39: 1.6170381e+08 | E39: 66906.56 | F39: 16779
A40: TOTAL | B40: FORMULA | C40: =+C35+C36-C37+C38-C39 -> 7.8754639e+08 | D40: =+D35+D36-D37+D38-D39 -> 1.3063286e+09 | E40: =+E35+E36-E37+E38-E39 -> 15273146 | F40: =+F35+F36-F37+F38-F39 -> 1417884.3
A41: SALDO LIBROS | B41: MANUAL | C41: 7.876938e+08 | D41: 1.469994e+09 | E41: 15742146 | F41: 1417884.3
A42: DIFERENCIA | B42: DEBE SER CERO | C42: =+C40-C41 -> -147408 | D42: =+D40-D41 -> -163665458 | E42: =+E40-E41 -> -469000 | F42: =+F40-F41 -> 0
A45: BANCO | C45: =SUM(C4+C37-C38+C7-C8+C5-C6) -> 7.85102e+08 | D45: =SUM(D4+D37-D38+D7-D8+D5-D6) -> 1.5326186e+09 | E45: =SUM(E4+E37-E38+E7-E8+E5-E6) -> 23225816 | F45: =SUM(F4+F37-F38+F7-F8+F5-F6) -> 1417884.3 | I45: Validar formulacion, arrastra saldos anteriores
A46: LIBROS | C46: =SUM(C10-C39+C36) -> 7.876938e+08 | D46: =SUM(D10-D39+D36) -> 1.469994e+09 | E46: =SUM(E10-E39+E36) -> 15742146 | F46: =SUM(F10-F39+F36) -> 1417884.3
